python_a2a/__init__.py
python_a2a/cli.py
python_a2a/client.py
python_a2a/exceptions.py
python_a2a/py.typed
python_a2a/agent_flow/__init__.py
python_a2a/agent_flow/cli.py
python_a2a/agent_flow/engine/__init__.py
python_a2a/agent_flow/engine/executor.py
python_a2a/agent_flow/examples/__init__.py
python_a2a/agent_flow/models/__init__.py
python_a2a/agent_flow/models/agent.py
python_a2a/agent_flow/models/tool.py
python_a2a/agent_flow/models/workflow.py
python_a2a/agent_flow/server/__init__.py
python_a2a/agent_flow/server/agent_api.py
python_a2a/agent_flow/server/api.py
python_a2a/agent_flow/server/web.py
python_a2a/agent_flow/server/static/__init__.py
python_a2a/agent_flow/server/static/css/__init__.py
python_a2a/agent_flow/server/static/css/flow-builder.css
python_a2a/agent_flow/server/static/css/main.css
python_a2a/agent_flow/server/static/css/network-execution.css
python_a2a/agent_flow/server/static/images/__init__.py
python_a2a/agent_flow/server/static/images/favicon.ico
python_a2a/agent_flow/server/static/js/__init__.py
python_a2a/agent_flow/server/static/js/flow-builder.js
python_a2a/agent_flow/server/static/js/network-execution.js
python_a2a/agent_flow/server/static/js/simple-workflow-editor.js
python_a2a/agent_flow/server/static/js/workflow-editor.js
python_a2a/agent_flow/server/templates/404.html
python_a2a/agent_flow/server/templates/500.html
python_a2a/agent_flow/server/templates/__init__.py
python_a2a/agent_flow/server/templates/agents.html
python_a2a/agent_flow/server/templates/index.html
python_a2a/agent_flow/server/templates/tools.html
python_a2a/agent_flow/server/templates/workflows.html
python_a2a/agent_flow/storage/__init__.py
python_a2a/agent_flow/storage/workflow_storage.py
python_a2a/agent_flow/utils/__init__.py
python_a2a/agent_flow/utils/agent_manager.py
python_a2a/client/__init__.py
python_a2a/client/base.py
python_a2a/client/http.py
python_a2a/client/network.py
python_a2a/client/router.py
python_a2a/client/streaming.py
python_a2a-0.5.8.dist-info/licenses/LICENSE
python_a2a-0.5.8.dist-info/METADATA
python_a2a-0.5.8.dist-info/WHEEL
python_a2a-0.5.8.dist-info/entry_points.txt
python_a2a-0.5.8.dist-info/top_level.txt
python_a2a-0.5.8.dist-info/RECORD
