Metadata-Version: 2.4
Name: python-a2a
Version: 0.5.8
Summary: A comprehensive Python library for Google's Agent-to-Agent (A2A) protocol
Home-page: https://github.com/themanojdesai/python-a2a
Author: Manoj Desai
Author-email: Manoj Desai <themanojdesai@gmail.com>
License: MIT
Project-URL: Homepage, https://github.com/themanojdesai/python-a2a
Project-URL: Bug Tracker, https://github.com/themanojdesai/python-a2a/issues
Project-URL: Documentation, https://python-a2a.readthedocs.io
Project-URL: Source Code, https://github.com/themanojdesai/python-a2a
Keywords: a2a,agent,ai,llm,interoperability,google,protocol,chatbot,openai,anthropic,claude,huggingface,mcp,model-context-protocol,aws-bedrock,langchain
Classifier: Development Status :: 4 - Beta
Classifier: Intended Audience :: Developers
Classifier: License :: OSI Approved :: MIT License
Classifier: Operating System :: OS Independent
Classifier: Programming Language :: Python :: 3.9
Classifier: Programming Language :: Python :: 3.10
Classifier: Programming Language :: Python :: 3.11
Classifier: Topic :: Scientific/Engineering :: Artificial Intelligence
Classifier: Topic :: Software Development :: Libraries
Classifier: Topic :: Software Development :: Libraries :: Python Modules
Requires-Python: >=3.9
License-File: LICENSE
Requires-Dist: requests>=2.25.0
Requires-Dist: flask>=2.0.0
Requires-Dist: aiohttp>=3.8.0
Requires-Dist: openai>=1.0.0
Requires-Dist: anthropic>=0.3.0
Requires-Dist: boto3>=1.26.0
Requires-Dist: botocore>=1.29.0
Requires-Dist: httpx>=0.23.0
Requires-Dist: fastapi>=0.95.0
Requires-Dist: uvicorn>=0.21.0
Requires-Dist: pydantic>=1.10.7
Requires-Dist: langchain>=0.1.0
Provides-Extra: dev
Requires-Dist: pytest>=6.0.0; extra == "dev"
Requires-Dist: pytest-cov>=2.12.0; extra == "dev"
Requires-Dist: black>=21.5b2; extra == "dev"
Requires-Dist: flake8>=3.9.2; extra == "dev"
Requires-Dist: mypy>=0.812; extra == "dev"
Requires-Dist: responses>=0.13.3; extra == "dev"
Provides-Extra: server
Requires-Dist: flask>=2.0.0; extra == "server"
Requires-Dist: aiohttp>=3.8.0; extra == "server"
Provides-Extra: openai
Requires-Dist: openai>=1.0.0; extra == "openai"
Provides-Extra: anthropic
Requires-Dist: anthropic>=0.3.0; extra == "anthropic"
Provides-Extra: bedrock
Requires-Dist: boto3>=1.26.0; extra == "bedrock"
Requires-Dist: botocore>=1.29.0; extra == "bedrock"
Provides-Extra: mcp
Requires-Dist: httpx>=0.23.0; extra == "mcp"
Requires-Dist: fastapi>=0.95.0; extra == "mcp"
Requires-Dist: uvicorn>=0.21.0; extra == "mcp"
Requires-Dist: pydantic>=1.10.7; extra == "mcp"
Provides-Extra: langchain
Requires-Dist: langchain>=0.1.0; extra == "langchain"
Provides-Extra: all
Requires-Dist: flask>=2.0.0; extra == "all"
Requires-Dist: openai>=1.0.0; extra == "all"
Requires-Dist: anthropic>=0.3.0; extra == "all"
Requires-Dist: boto3>=1.26.0; extra == "all"
Requires-Dist: botocore>=1.29.0; extra == "all"
Requires-Dist: httpx>=0.23.0; extra == "all"
Requires-Dist: fastapi>=0.95.0; extra == "all"
Requires-Dist: uvicorn>=0.21.0; extra == "all"
Requires-Dist: pydantic>=1.10.7; extra == "all"
Requires-Dist: aiohttp>=3.8.0; extra == "all"
Requires-Dist: langchain>=0.1.0; extra == "all"
Dynamic: author
Dynamic: home-page
Dynamic: license-file
Dynamic: requires-python
